LICENSE
MANIFEST.in
README.rst
setup.cfg
setup.py
bin/html_pyboleto_sample.py
bin/pdf_pyboleto_sample.py
pyboleto/__init__.py
pyboleto/data.py
pyboleto/html.py
pyboleto/pdf.py
pyboleto.egg-info/PKG-INFO
pyboleto.egg-info/SOURCES.txt
pyboleto.egg-info/dependency_links.txt
pyboleto.egg-info/not-zip-safe
pyboleto.egg-info/requires.txt
pyboleto.egg-info/top_level.txt
pyboleto/bank/__init__.py
pyboleto/bank/bancodobrasil.py
pyboleto/bank/banrisul.py
pyboleto/bank/bradesco.py
pyboleto/bank/caixa.py
pyboleto/bank/caixa_sigcb.py
pyboleto/bank/hsbc.py
pyboleto/bank/itau.py
pyboleto/bank/real.py
pyboleto/bank/santander.py
pyboleto/bank/sicredi.py
pyboleto/django/__init__.py
pyboleto/django/admin.py
pyboleto/django/models.py
pyboleto/django/views.py
pyboleto/media/logo_bancobradesco.jpg
pyboleto/media/logo_bancocaixa.jpg
pyboleto/media/logo_bancohsbc.jpg
pyboleto/media/logo_bancoreal.jpg
pyboleto/media/logo_banrisul.jpg
pyboleto/media/logo_bb.jpg
pyboleto/media/logo_itau.jpg
pyboleto/media/logo_santander.jpg
pyboleto/media/logo_sicredi.jpg
pyboleto/templates/head.html
pyboleto/templates/recibo_caixa.html
pyboleto/templates/recibo_sacado.html
tests/__init__.py
tests/__init__.pyc
tests/alltests.py
tests/alltests.pyc
tests/test_banco_banrisul.py
tests/test_banco_banrisul.pyc
tests/test_banco_bradesco.py
tests/test_banco_bradesco.pyc
tests/test_banco_caixa.py
tests/test_banco_caixa.pyc
tests/test_banco_do_brasil.py
tests/test_banco_do_brasil.pyc
tests/test_banco_hsbc.py
tests/test_banco_hsbc.pyc
tests/test_banco_hsbc_com_registro.py
tests/test_banco_hsbc_com_registro.pyc
tests/test_banco_itau.py
tests/test_banco_itau.pyc
tests/test_banco_real.py
tests/test_banco_real.pyc
tests/test_banco_santander.py
tests/test_banco_santander.pyc
tests/testutils.py
tests/testutils.pyc
tests/__pycache__/__init__.cpython-35.pyc
tests/__pycache__/alltests.cpython-35.pyc
tests/__pycache__/test_banco_banrisul.cpython-35.pyc
tests/__pycache__/test_banco_bradesco.cpython-35.pyc
tests/__pycache__/test_banco_caixa.cpython-35.pyc
tests/__pycache__/test_banco_do_brasil.cpython-35.pyc
tests/__pycache__/test_banco_hsbc.cpython-35.pyc
tests/__pycache__/test_banco_hsbc_com_registro.cpython-35.pyc
