Metadata-Version: 1.1
Name: pyboleto
Version: 0.3.1
Summary: Python Library to create "boletos de cobrança bancária" for     several Brazilian banks
Home-page: https://github.com/eduardocereto/pyboleto
Author: Eduardo Cereto Carvalho
Author-email: eduardocereto@gmail.com
License: BSD
Download-URL: http://pypi.python.org/pypi/pyboleto
Platform: any
Classifier: Development Status :: 4 - Beta
Classifier: Operating System :: OS Independent
Classifier: Intended Audience :: Developers
Classifier: Intended Audience :: Financial and Insurance Industry
Classifier: Operating System :: OS Independent
Classifier: License :: OSI Approved :: BSD License
Classifier: Natural Language :: Portuguese (Brazilian)
Classifier: Programming Language :: Python
Classifier: Programming Language :: Python :: 3
Classifier: Programming Language :: Python :: 2.7
Classifier: Programming Language :: Python :: 2.6
Classifier: Topic :: Office/Business :: Financial
Classifier: Topic :: Software Development :: Libraries :: Python Modules
Classifier: Framework :: Django
Provides: pyboleto
